emfacilities/__init__.py
emfacilities/bibtex.py
emfacilities/constants.py
emfacilities/facilityLogo.png
emfacilities/protocols.conf
emfacilities/protocols/__init__.py
emfacilities/protocols/getnifs.py
emfacilities/protocols/protocol_OSCEM_metadata.py
emfacilities/protocols/protocol_data_counter.py
emfacilities/protocols/protocol_data_sampler.py
emfacilities/protocols/protocol_good_classes_extractor.py
emfacilities/protocols/protocol_monitor.py
emfacilities/protocols/protocol_monitor_2d_streamer.py
emfacilities/protocols/protocol_monitor_ctf.py
emfacilities/protocols/protocol_monitor_movie_gain.py
emfacilities/protocols/protocol_monitor_summary.py
emfacilities/protocols/protocol_monitor_system.py
emfacilities/protocols/protocol_trackUsedItems.py
emfacilities/protocols/protocol_volume_extractor.py
emfacilities/protocols/pynvml.py
emfacilities/protocols/report_html.py
emfacilities/protocols/report_influx.py
emfacilities/protocols/summary_provider.py
emfacilities/protocols/transport.py
emfacilities/tests/__init__.py
emfacilities/tests/protocols/__init__.py
emfacilities/tests/protocols/test_protocol_OSCEM_metadata.py
emfacilities/tests/protocols/test_protocol_data_counter.py
emfacilities/tests/protocols/test_protocol_data_sampler.py
emfacilities/tests/protocols/test_protocol_good_classes_extractor.py
emfacilities/tests/protocols/test_protocol_volume_extractor.py
emfacilities/tests/protocols/test_protocols_ctf_monitor.py
emfacilities/tests/protocols/test_protocols_ctf_streaming.py
emfacilities/tests/protocols/test_protocols_system_monitor.py
emfacilities/tests/workflows/__init__.py
emfacilities/tests/workflows/test_workflow.py
emfacilities/tests/workflows/test_workflow_high_throughput.py
emfacilities/tests/workflows/test_workflow_streaming.py
emfacilities/viewers/__init__.py
emfacilities/viewers/viewer_good_classes_extractor.py
emfacilities/viewers/viewer_monitors.py
emfacilities/viewers/viewer_oscem_metadata.py
scipion_em_facilities-3.3.1.dist-info/LICENSE
scipion_em_facilities-3.3.1.dist-info/METADATA
scipion_em_facilities-3.3.1.dist-info/WHEEL
scipion_em_facilities-3.3.1.dist-info/entry_points.txt
scipion_em_facilities-3.3.1.dist-info/top_level.txt
scipion_em_facilities-3.3.1.dist-info/RECORD
