Metadata-Version: 2.1
Name: scipion-em-facilities
Version: 3.3.1
Summary: Plugin to use Scipion in facilities
License: GNU General Public License v3 (GPLv3)
Project-URL: Homepage, https://github.com/scipion-em/scipion-em-facilities
Project-URL: Issues, https://github.com/scipion-em/scipion-em-facilities/issues
Keywords: scipion electron-microscopy cryo-em structural-biology image-processing scipion-3.0 Facilities Facility Streaming
Requires-Python: >=3.8
License-File: LICENSE
Requires-Dist: scipion-pyworkflow>=3.0.31
Requires-Dist: scipion-em
Requires-Dist: nvidia-ml-py3
Requires-Dist: pytz
Requires-Dist: paramiko
Requires-Dist: influxdb
Requires-Dist: joblib
Requires-Dist: networkx
Requires-Dist: scipion-em-xmipp
Requires-Dist: pyyaml
